py2dmat/__init__.py
py2dmat/_info.py
py2dmat/_main.py
py2dmat/_message.py
py2dmat/_runner.py
py2dmat/algorithm/__init__.py
py2dmat/algorithm/_algorithm.py
py2dmat/algorithm/bayes.py
py2dmat/algorithm/exchange.py
py2dmat/algorithm/mapper_mpi.py
py2dmat/algorithm/min_search.py
py2dmat/algorithm/montecarlo.py
py2dmat/algorithm/pamc.py
py2dmat/exception.py
py2dmat/mpi.py
py2dmat/solver/__init__.py
py2dmat/solver/_solver.py
py2dmat/solver/analytical.py
py2dmat/solver/function.py
py2dmat/solver/leed.py
py2dmat/solver/lib_make_convolution.py
py2dmat/solver/sim_trhepd_rheed.py
py2dmat/solver/sxrd.py
py2dmat/util/__init__.py
py2dmat/util/graph.py
py2dmat/util/limitation.py
py2dmat/util/mapping.py
py2dmat/util/neighborlist.py
py2dmat/util/read_matrix.py
py2dmat/util/resampling.py
py2dmat/util/separateT.py
py2dmat/util/toml.py
py2dmat-2.2.1.dist-info/LICENSE
py2dmat-2.2.1.dist-info/METADATA
py2dmat-2.2.1.dist-info/WHEEL
py2dmat-2.2.1.dist-info/entry_points.txt
py2dmat-2.2.1.dist-info/RECORD
