Metadata-Version: 2.3
Name: py2dmat
Version: 2.2.1
Summary: Data-analysis software of quantum beam diffraction experiments for 2D material structure
License: GPL-3.0-or-later
Author: 2DMAT developers
Author-email: 2dmat-dev@issp.u-tokyo.ac.jp
Requires-Python: >=3.6.8
Classifier: License :: OSI Approved :: GNU General Public License v3 or later (GPLv3+)
Classifier: Programming Language :: Python :: 3
Classifier: Programming Language :: Python :: 3.7
Classifier: Programming Language :: Python :: 3.8
Classifier: Programming Language :: Python :: 3.9
Classifier: Programming Language :: Python :: 3.10
Classifier: Programming Language :: Python :: 3.11
Classifier: Programming Language :: Python :: 3.12
Classifier: Programming Language :: Python :: 3.13
Provides-Extra: all
Provides-Extra: bayes
Provides-Extra: exchange
Provides-Extra: min-search
Requires-Dist: mpi4py (>=3,<4) ; extra == "exchange" or extra == "all"
Requires-Dist: numpy (>=1.14,<2.0)
Requires-Dist: physbo (>=1.0.0) ; extra == "bayes" or extra == "all"
Requires-Dist: scipy (>=1,<2) ; extra == "min-search" or extra == "all"
Requires-Dist: tomli (>=1.2)
Project-URL: Repository, https://github.com/issp-center-dev/2DMAT
